unitsit_tools/__init__.py
unitsit_tools/config/JSON.py
unitsit_tools/config/Properties.py
unitsit_tools/config/Toml.py
unitsit_tools/config/XML.py
unitsit_tools/config/YAML.py
unitsit_tools/config/__init__.py
unitsit_tools/database/AsyncPG.py
unitsit_tools/database/PsycoPG.py
unitsit_tools/database/__init__.py
unitsit_tools/logger/DjangoLogParser.py
unitsit_tools/logger/LogParser.py
unitsit_tools/logger/RotatingLog.py
unitsit_tools/logger/TimedRotatingLog.py
unitsit_tools/logger/__init__.py
unitsit_tools/misc/Timing.py
unitsit_tools/misc/__init__.py
unitsit_tools-1.2.3.dist-info/METADATA
unitsit_tools-1.2.3.dist-info/WHEEL
unitsit_tools-1.2.3.dist-info/RECORD
