Metadata-Version: 2.1
Name: unitsit-tools
Version: 1.2.3
Summary: unitsit-tools is a Python package containing various utility modules for common tasks.
License: MIT
Author: NoirPi
Author-email: noirpi@noircoding.de
Requires-Python: >=3.8,<4.0
Classifier: License :: OSI Approved :: MIT License
Classifier: Programming Language :: Python :: 3
Classifier: Programming Language :: Python :: 3.8
Classifier: Programming Language :: Python :: 3.9
Classifier: Programming Language :: Python :: 3.10
Classifier: Programming Language :: Python :: 3.11
Classifier: Programming Language :: Python :: 3.12
Provides-Extra: asyncpg
Provides-Extra: psycopg
Requires-Dist: asyncpg (>=0.28,<0.29) ; extra == "asyncpg"
Requires-Dist: psycopg-binary (>=3.1,<4.0) ; extra == "psycopg"
Requires-Dist: toml (>=0.10,<0.11)
